uipath_connectors/microsoft_github/__init__.py
uipath_connectors/microsoft_github/client.py
uipath_connectors/microsoft_github/errors.py
uipath_connectors/microsoft_github/py.typed
uipath_connectors/microsoft_github/types.py
uipath_connectors/microsoft_github/api/__init__.py
uipath_connectors/microsoft_github/api/create_branch/__init__.py
uipath_connectors/microsoft_github/api/create_branch/create_branch.py
uipath_connectors/microsoft_github/api/create_issues/__init__.py
uipath_connectors/microsoft_github/api/create_issues/create_issue.py
uipath_connectors/microsoft_github/api/create_pulls/__init__.py
uipath_connectors/microsoft_github/api/create_pulls/create_pull.py
uipath_connectors/microsoft_github/api/create_repos/__init__.py
uipath_connectors/microsoft_github/api/create_repos/create_repo.py
uipath_connectors/microsoft_github/api/download_file/__init__.py
uipath_connectors/microsoft_github/api/download_file/download_file.py
uipath_connectors/microsoft_github/api/list_branches/__init__.py
uipath_connectors/microsoft_github/api/list_branches/list_all_branches.py
uipath_connectors/microsoft_github/api/merge_pull_request/__init__.py
uipath_connectors/microsoft_github/api/merge_pull_request/merge_pull.py
uipath_connectors/microsoft_github/api/search_issues/__init__.py
uipath_connectors/microsoft_github/api/search_issues/search_issues.py
uipath_connectors/microsoft_github/api/search_repositories/__init__.py
uipath_connectors/microsoft_github/api/search_repositories/search_repos.py
uipath_connectors/microsoft_github/api/update_issues/__init__.py
uipath_connectors/microsoft_github/api/update_issues/update_issue.py
uipath_connectors/microsoft_github/models/__init__.py
uipath_connectors/microsoft_github/models/create_branch_request.py
uipath_connectors/microsoft_github/models/create_branch_response.py
uipath_connectors/microsoft_github/models/create_branch_response_object.py
uipath_connectors/microsoft_github/models/create_issue_request.py
uipath_connectors_microsoft_github-2.3.48.dev12.dist-info/METADATA
uipath_connectors_microsoft_github-2.3.48.dev12.dist-info/WHEEL
uipath_connectors_microsoft_github-2.3.48.dev12.dist-info/entry_points.txt
uipath_connectors_microsoft_github-2.3.48.dev12.dist-info/top_level.txt
uipath_connectors_microsoft_github-2.3.48.dev12.dist-info/RECORD
